bl60x_flash/__init__.py
bl60x_flash/contrib/bootheader.bin
bl60x_flash/contrib/eflash_loader_40m.bin
bl60x_flash/main.py
bl60x_flash-0.1.5.dist-info/entry_points.txt
bl60x_flash-0.1.5.dist-info/LICENSE
bl60x_flash-0.1.5.dist-info/WHEEL
bl60x_flash-0.1.5.dist-info/METADATA
bl60x_flash-0.1.5.dist-info/RECORD
