Metadata-Version: 2.1
Name: bl60x-flash
Version: 0.1.5
Summary: Flash tool for Bouffalo Labs BL60x UART bootloader
License: MIT
Author: Stefan Schake
Author-email: stschake@gmail.com
Requires-Python: >=3.8,<4.0
Classifier: License :: OSI Approved :: MIT License
Classifier: Programming Language :: Python :: 3
Classifier: Programming Language :: Python :: 3.8
Classifier: Programming Language :: Python :: 3.9
Requires-Dist: pyserial (>=3.4,<4.0)
Requires-Dist: tqdm (>=4.51.0,<5.0.0)
